MANIFEST.in
setup.cfg
setup.py
requirements/base.txt
requirements/dev.txt
xls_writer/__init__.py
xls_writer/api.py
xls_writer/csv_formatter.py
xls_writer/detail.py
xls_writer/exceptions.py
xls_writer/field.py
xls_writer/utils.py
xls_writer.egg-info/PKG-INFO
xls_writer.egg-info/SOURCES.txt
xls_writer.egg-info/dependency_links.txt
xls_writer.egg-info/top_level.txt
xls_writer_test/__init__.py
xls_writer_test/helpers.py
xls_writer_test/test_empty_check.py
xls_writer_test/test_field.py
xls_writer_test/test_field_builder.py
xls_writer_test/test_field_reader.py
xls_writer_test/test_formatter.py
xls_writer_test/test_utils.py