Metadata-Version: 1.0
Name: xls-writer
Version: 0.2.0
Summary: A simple utility to format tabular data from python objects.
Home-page: UNKNOWN
Author: Jacek Bzdak
Author-email: jacek@askesis.pl
License: All Rights reserved
Platform: UNKNOWN
